pyeconet/__init__.py
pyeconet/api.py
pyeconet/errors.py
pyeconet/equipment/__init__.py
pyeconet/equipment/thermostat.py
pyeconet/equipment/water_heater.py
pyeconet-0.2.1.dist-info/licenses/LICENSE
pyeconet-0.2.1.dist-info/METADATA
pyeconet-0.2.1.dist-info/WHEEL
pyeconet-0.2.1.dist-info/top_level.txt
pyeconet-0.2.1.dist-info/RECORD
