Metadata-Version: 2.4
Name: pyeconet
Version: 0.2.1
Summary: Interface to the unofficial EcoNet API
Home-page: https://github.com/w1ll1am23/pyeconet
Author: William Scanlon
Project-URL: Bug Reports, https://github.com/w1ll1am23/pyeconet/issues
Project-URL: Source, https://github.com/w1ll1am23/pyeconet
Keywords: econet,rheem,api
Classifier: License :: OSI Approved :: MIT License
Requires-Python: >=3.8, <4
License-File: LICENSE
Requires-Dist: aiohttp<4,>=3.11.11
Requires-Dist: paho-mqtt<3,>=2.1.0
Dynamic: author
Dynamic: classifier
Dynamic: description
Dynamic: description-content-type
Dynamic: home-page
Dynamic: keywords
Dynamic: license-file
Dynamic: project-url
Dynamic: requires-dist
Dynamic: requires-python
Dynamic: summary
